{
  "versionCode": 108,
  "versionName": "V1.0.8",
  "title": "发现新版本 V1.0.8 build108",
  "content": [
    "修复 Ping 仅 IPv4 模式在部分 Android ROM 全程超时的问题",
    "自动 Ping 明确解析并显示实际协议，避免异常 0ms 显示",
    "Ping 图表显示当前目标和实际协议",
    "目标地址和 Ping 地址增加最近 5 条历史，可点选和删除",
    "保持 V1.0.7 的 NAT 判定、运营商识别和高性能定速发射核心"
  ],
  "apkUrl": "https://github.com/OnlyChallgener/NetSessionTester/releases/download/v1.0.8-108/NetSessionTester-V1.0.8-build108-signed.apk",
  "githubUrl": "https://github.com/OnlyChallgener/NetSessionTester/releases/latest",
  "force": false
}
